setup.py
pyrecon.egg-info/PKG-INFO
pyrecon.egg-info/SOURCES.txt
pyrecon.egg-info/dependency_links.txt
pyrecon.egg-info/not-zip-safe
pyrecon.egg-info/top_level.txt
recon/__init__.py
recon/meld.py
recon/serial.py
recon/trans.py
recon/util.py
recon/wall.py
scripts/dsres2meld
scripts/meld_info
scripts/wall2meld
scripts/wall_info