Metadata-Version: 1.0
Name: pyrecon
Version: 0.3.0
Summary: Python implementation of Recon file format and utilities
Home-page: http://github.com/xogeny/recon/
Author: Michael Tiller
Author-email: michael.tiller@gmail.com
License: MIT
Platform: UNKNOWN
